Async_fifo.sv
module fifo2 (rdata, wfull, rempty, wdata, winc, wclk, wrst_n, rinc, rclk, rrst_n);
    parameter DSIZE = 8;
    parameter ASIZE = 6;

    output [DSIZE-1:0] rdata;
    output wfull;
    output rempty;
    input [DSIZE-1:0] wdata;
    input winc, wclk, wrst_n;
    input rinc, rclk, rrst_n;
    wire [ASIZE-1:0] wptr, rptr;  
    wire [ASIZE-1:0] waddr, raddr; 

    async_cmp #(ASIZE) async_cmp(.aempty_n(aempty_n), .afull_n(afull_n), .wptr(wptr), .rptr(rptr), .wrst_n(wrst_n));
    fifomem #(DSIZE, ASIZE) fifomem(.rdata(rdata), .wdata(wdata), .waddr(wptr), .raddr(rptr), .wclken(winc), .wclk(wclk));
    rptr_empty #(ASIZE) rptr_empty(.rempty(rempty), .rptr(rptr), .aempty_n(aempty_n), .rinc(rinc),.rclk(rclk), .rrst_n(rrst_n));
    wptr_full #(ASIZE) wptr_full (.wfull(wfull), .wptr(wptr), .afull_n(afull_n), .winc(winc), .wclk(wclk), .wrst_n(wrst_n));

endmodule

module fifomem (rdata, wdata, waddr, raddr, wclken, wclk);
    parameter DATASIZE = 8; // data width
    parameter ADDRSIZE = 6; // memory address bits
    parameter DEPTH = 1<<ADDRSIZE; // DEPTH = 2**ADDRSIZE

    output [DATASIZE-1:0] rdata;
    input [DATASIZE-1:0] wdata;
    input [ADDRSIZE-1:0] waddr, raddr;
    input wclken, wclk;
/////////// memory array//////////////
    reg [DATASIZE-1:0] MEM [0:DEPTH-1];
  assign rdata = MEM[raddr]; ////////reading from FIFO
    always @(posedge wclk)
      if (wclken) MEM[waddr] <= wdata; ///writing to the FIFO

endmodule

module async_cmp (aempty_n, afull_n, wptr, rptr, wrst_n);
    parameter ADDRSIZE = 6;
    parameter N = ADDRSIZE-1;

    output aempty_n, afull_n;
    input [N:0] wptr, rptr;
    input wrst_n;
    reg direction;
    wire high = 1'b1;
  ///////////////// Direction setting logic/////////////////////
    wire dirset_n = ~( (wptr[N]^rptr[N-1]) & ~(wptr[N-1]^rptr[N]));
    wire dirclr_n = ~((~(wptr[N]^rptr[N-1]) & (wptr[N-1]^rptr[N])) | ~wrst_n);
    always @(posedge high or negedge dirset_n or negedge dirclr_n)
        if (!dirclr_n) direction <= 1'b0;
        else if (!dirset_n) direction <= 1'b1;
        else direction <= high;
  
   /////////// FIFO full and empty conditions//////////
    assign aempty_n = ~((wptr == rptr) && !direction);
    assign afull_n = ~((wptr == rptr) && direction);

endmodule
///////////// Read Pointer Management
module rptr_empty (rempty, rptr, aempty_n, rinc, rclk, rrst_n);
    parameter ADDRSIZE = 6;

    output rempty;
    output [ADDRSIZE-1:0] rptr;
    input aempty_n;
    input rinc, rclk, rrst_n;
    reg [ADDRSIZE-1:0] rptr, rbin;
    reg rempty, rempty2;
    wire [ADDRSIZE-1:0] rgnext, rbnext;
///////// Update read pointer in binary and Gray code
    always @(posedge rclk or negedge rrst_n)
        if (!rrst_n) begin
        rbin <= 0;
        rptr <= 0;
        end
        else begin
        rbin <= rbnext;
        rptr <= rgnext;
        end
  ////// Increment binary counter if FIFO is not empty
    assign rbnext = !rempty ? rbin + rinc : rbin;
  assign rgnext = (rbnext>>1) ^ rbnext; //// binary-to-gray conversion
    always @(posedge rclk or negedge aempty_n)
        if (!aempty_n) {rempty,rempty2} <= 2'b11;
        else {rempty,rempty2} <= {rempty2,~aempty_n};

endmodule
//////////// Write Pointer Management
module wptr_full (wfull, wptr, afull_n, winc, wclk, wrst_n);
    parameter ADDRSIZE = 6;
    
    output wfull;
    output [ADDRSIZE-1:0] wptr;
    input afull_n;
    input winc, wclk, wrst_n;
    reg [ADDRSIZE-1:0] wptr, wbin;
    reg wfull, wfull2;
    wire [ADDRSIZE-1:0] wgnext, wbnext;
// Update write pointer in binary and Gray code
    always @(posedge wclk or negedge wrst_n)
        if (!wrst_n) begin
        wbin <= 0;
        wptr <= 0;
        end
        else begin
        wbin <= wbnext;
        wptr <= wgnext;
        end
// Increment binary counter if FIFO is not full
    assign wbnext = !wfull ? wbin + winc : wbin;
    assign wgnext = (wbnext>>1) ^ wbnext; // binary-to-gray conversion
  // Update full flag
    always @(posedge wclk or negedge wrst_n or negedge afull_n)
        if (!wrst_n ) {wfull,wfull2} <= 2'b00;
        else if (!afull_n) {wfull,wfull2} <= 2'b11;
        else {wfull,wfull2} <= {wfull2,~afull_n};

endmodule

Milestone_1/Async_fifo_tb.sv
module top;

    // Parameters
    localparam DSIZE = 8; // Data size
    localparam ASIZE = 6; // Address size
    localparam CLK_PERIOD_WR = 12.5; // Write clock period in ns
    localparam CLK_PERIOD_RD = 20; // Read clock period in ns

    reg [DSIZE-1:0] wdata;
    reg winc, wclk, wrst_n;
    reg rinc, rclk, rrst_n;
    wire [DSIZE-1:0] rdata;
    wire wfull, rempty;

 /////// Instantiate the Unit Under Test (UUT)
    fifo2 #(
        .DSIZE(DSIZE),
        .ASIZE(ASIZE)
    ) uut (
        .rdata(rdata),
        .wfull(wfull),
        .rempty(rempty),
        .wdata(wdata),
        .winc(winc),
        .wclk(wclk),
        .wrst_n(wrst_n),
        .rinc(rinc),
        .rclk(rclk),
        .rrst_n(rrst_n)
    );

 //////// Clock generation
    always #(CLK_PERIOD_WR/2) wclk = ~wclk;
    always #(CLK_PERIOD_RD/2) rclk = ~rclk;

    // Test sequence
    initial begin
        // Initializing all the signals to zero
        wclk = 0;
        rclk = 0;
        wrst_n = 0;
        rrst_n = 0;
        winc = 0;
        rinc = 0;
        wdata = 0;

        // Reseting the system
        #(CLK_PERIOD_WR*2) wrst_n = 1;
        #(CLK_PERIOD_RD*2) rrst_n = 1;

        // Writing 120 items to fifo
        repeat (120) begin
            @(posedge wclk) begin
                if (!wfull) begin
                    wdata <= wdata + 1;
                    winc <= 1;
                end else begin
                    winc <= 0;
                end
            end
        end

        // Wait for some cycle
        #(CLK_PERIOD_WR*10);

        // reading 120 items to fifo
        repeat (120) begin
            @(posedge rclk) begin
                if (!rempty) begin
                    rinc <= 1;
                end else begin
                    rinc <= 0;
                end
            end
        end

        // Complete
        #(CLK_PERIOD_RD*10);
        $finish;
    end

    // Monitor the data 
    initial begin
        $monitor("Time=%t, wdata=%d, rdata=%d, wfull=%b, rempty=%b", $time, wdata, rdata, wfull, rempty);
    end
initial 
  begin
    $dumpfile("dump.vcd");
    $dumpvars;
  end
endmodule

Milestone_1/dump.vcd
$date
	Fri Jan 31 21:02:11 2025
$end
$version
	QuestaSim Version 2024.2
$end
$timescale
	1ns
$end

$scope module top $end
$var parameter 32 ! DSIZE $end
$var parameter 32 " ASIZE $end
$var parameter 0 # CLK_PERIOD_WR $end
$var parameter 32 $ CLK_PERIOD_RD $end
$var reg 8 % wdata [7:0] $end
$var reg 1 & winc $end
$var reg 1 ' wclk $end
$var reg 1 ( wrst_n $end
$var reg 1 ) rinc $end
$var reg 1 * rclk $end
$var reg 1 + rrst_n $end
$var wire 1 , rdata [7] $end
$var wire 1 - rdata [6] $end
$var wire 1 . rdata [5] $end
$var wire 1 / rdata [4] $end
$var wire 1 0 rdata [3] $end
$var wire 1 1 rdata [2] $end
$var wire 1 2 rdata [1] $end
$var wire 1 3 rdata [0] $end
$var wire 1 4 wfull $end
$var wire 1 5 rempty $end

$scope module uut $end
$var parameter 32 6 DSIZE $end
$var parameter 32 7 ASIZE $end
$var wire 1 , rdata [7] $end
$var wire 1 - rdata [6] $end
$var wire 1 . rdata [5] $end
$var wire 1 / rdata [4] $end
$var wire 1 0 rdata [3] $end
$var wire 1 1 rdata [2] $end
$var wire 1 2 rdata [1] $end
$var wire 1 3 rdata [0] $end
$var wire 1 4 wfull $end
$var wire 1 5 rempty $end
$var wire 1 8 wdata [7] $end
$var wire 1 9 wdata [6] $end
$var wire 1 : wdata [5] $end
$var wire 1 ; wdata [4] $end
$var wire 1 < wdata [3] $end
$var wire 1 = wdata [2] $end
$var wire 1 > wdata [1] $end
$var wire 1 ? wdata [0] $end
$var wire 1 @ winc $end
$var wire 1 A wclk $end
$var wire 1 B wrst_n $end
$var wire 1 C rinc $end
$var wire 1 D rclk $end
$var wire 1 E rrst_n $end
$var wire 1 F wptr [5] $end
$var wire 1 G wptr [4] $end
$var wire 1 H wptr [3] $end
$var wire 1 I wptr [2] $end
$var wire 1 J wptr [1] $end
$var wire 1 K wptr [0] $end
$var wire 1 L rptr [5] $end
$var wire 1 M rptr [4] $end
$var wire 1 N rptr [3] $end
$var wire 1 O rptr [2] $end
$var wire 1 P rptr [1] $end
$var wire 1 Q rptr [0] $end
$var wire 1 R waddr [5] $end
$var wire 1 S waddr [4] $end
$var wire 1 T waddr [3] $end
$var wire 1 U waddr [2] $end
$var wire 1 V waddr [1] $end
$var wire 1 W waddr [0] $end
$var wire 1 X raddr [5] $end
$var wire 1 Y raddr [4] $end
$var wire 1 Z raddr [3] $end
$var wire 1 [ raddr [2] $end
$var wire 1 \ raddr [1] $end
$var wire 1 ] raddr [0] $end
$var wire 1 ^ aempty_n $end
$var wire 1 _ afull_n $end

$scope module async_cmp $end
$var parameter 32 ` ADDRSIZE $end
$var parameter 32 a N $end
$var wire 1 ^ aempty_n $end
$var wire 1 _ afull_n $end
$var wire 1 F wptr [5] $end
$var wire 1 G wptr [4] $end
$var wire 1 H wptr [3] $end
$var wire 1 I wptr [2] $end
$var wire 1 J wptr [1] $end
$var wire 1 K wptr [0] $end
$var wire 1 L rptr [5] $end
$var wire 1 M rptr [4] $end
$var wire 1 N rptr [3] $end
$var wire 1 O rptr [2] $end
$var wire 1 P rptr [1] $end
$var wire 1 Q rptr [0] $end
$var wire 1 B wrst_n $end
$var reg 1 b direction $end
$var wire 1 c high $end
$var wire 1 d dirset_n $end
$var wire 1 e dirclr_n $end
$upscope $end

$scope module fifomem $end
$var parameter 32 f DATASIZE $end
$var parameter 32 g ADDRSIZE $end
$var parameter 32 h DEPTH $end
$var wire 1 , rdata [7] $end
$var wire 1 - rdata [6] $end
$var wire 1 . rdata [5] $end
$var wire 1 / rdata [4] $end
$var wire 1 0 rdata [3] $end
$var wire 1 1 rdata [2] $end
$var wire 1 2 rdata [1] $end
$var wire 1 3 rdata [0] $end
$var wire 1 8 wdata [7] $end
$var wire 1 9 wdata [6] $end
$var wire 1 : wdata [5] $end
$var wire 1 ; wdata [4] $end
$var wire 1 < wdata [3] $end
$var wire 1 = wdata [2] $end
$var wire 1 > wdata [1] $end
$var wire 1 ? wdata [0] $end
$var wire 1 F waddr [5] $end
$var wire 1 G waddr [4] $end
$var wire 1 H waddr [3] $end
$var wire 1 I waddr [2] $end
$var wire 1 J waddr [1] $end
$var wire 1 K waddr [0] $end
$var wire 1 L raddr [5] $end
$var wire 1 M raddr [4] $end
$var wire 1 N raddr [3] $end
$var wire 1 O raddr [2] $end
$var wire 1 P raddr [1] $end
$var wire 1 Q raddr [0] $end
$var wire 1 @ wclken $end
$var wire 1 A wclk $end
$upscope $end

$scope module rptr_empty $end
$var parameter 32 i ADDRSIZE $end
$var reg 1 j rempty $end
$var reg 6 k rptr [5:0] $end
$var wire 1 ^ aempty_n $end
$var wire 1 C rinc $end
$var wire 1 D rclk $end
$var wire 1 E rrst_n $end
$var reg 6 l rbin [5:0] $end
$var reg 1 m rempty2 $end
$var wire 1 n rgnext [5] $end
$var wire 1 o rgnext [4] $end
$var wire 1 p rgnext [3] $end
$var wire 1 q rgnext [2] $end
$var wire 1 r rgnext [1] $end
$var wire 1 s rgnext [0] $end
$var wire 1 t rbnext [5] $end
$var wire 1 u rbnext [4] $end
$var wire 1 v rbnext [3] $end
$var wire 1 w rbnext [2] $end
$var wire 1 x rbnext [1] $end
$var wire 1 y rbnext [0] $end
$upscope $end

$scope module wptr_full $end
$var parameter 32 z ADDRSIZE $end
$var reg 1 { wfull $end
$var reg 6 | wptr [5:0] $end
$var wire 1 _ afull_n $end
$var wire 1 @ winc $end
$var wire 1 A wclk $end
$var wire 1 B wrst_n $end
$var reg 6 } wbin [5:0] $end
$var reg 1 ~ wfull2 $end
$var wire 1 !! wgnext [5] $end
$var wire 1 "! wgnext [4] $end
$var wire 1 #! wgnext [3] $end
$var wire 1 $! wgnext [2] $end
$var wire 1 %! wgnext [1] $end
$var wire 1 &! wgnext [0] $end
$var wire 1 '! wbnext [5] $end
$var wire 1 (! wbnext [4] $end
$var wire 1 )! wbnext [3] $end
$var wire 1 *! wbnext [2] $end
$var wire 1 +! wbnext [1] $end
$var wire 1 ,! wbnext [0] $end
$upscope $end
$upscope $end
$upscope $end

$scope begin std $end
$upscope $end
$enddefinitions $end
#0
$dumpvars
b0 %
0&
0'
0(
0)
0*
0+
0b
1j
b0 k
b0 l
1m
0{
b0 |
b0 }
0~
b1000 !
b110 "
b10100 $
b1000 6
b110 7
b110 `
b101 a
b1000 f
b110 g
b1000000 h
b110 i
b110 z
r12.5 #
x3
x2
x1
x0
x/
x.
x-
x,
04
15
0K
0J
0I
0H
0G
0F
0Q
0P
0O
0N
0M
0L
zW
zV
zU
zT
zS
zR
z]
z\
z[
zZ
zY
zX
0^
1_
1c
1d
0e
0s
0r
0q
0p
0o
0n
0y
0x
0w
0v
0u
0t
0&!
0%!
0$!
0#!
0"!
0!!
0,!
0+!
0*!
0)!
0(!
0'!
0E
0D
0C
0B
0A
0@
0?
0>
0=
0<
0;
0:
09
08
$end
#6
1'
1A
#10
1*
1D
#12
0'
0A
#18
1'
1A
#20
0*
0D
#24
0'
0A
#25
1(
1B
1e
#30
1*
1'
1D
1A
#36
0'
0A
#40
0*
0D
#42
1'
1A
#48
0'
0A
#50
1*
1D
#54
1'
1A
#60
0*
0'
0D
0A
#65
1+
1E
#66
1'
1A
b1 %
1&
1?
1@
1,!
1&!
#70
1*
1D
#72
0'
0A
#78
1'
1A
b1 }
b1 |
b10 %
0?
1>
13
02
01
00
0/
0.
0-
0,
1K
0,!
1+!
1%!
1^
#80
0*
0D
#84
0'
0A
#90
1*
1'
1D
1A
b10 }
b11 |
0m
b11 %
1?
1J
1,!
0&!
#96
0'
0A
#100
0*
0D
#102
1'
1A
b11 }
b10 |
b100 %
0?
0>
1=
0K
0,!
0+!
1*!
1$!
#108
0'
0A
#110
1*
1D
0j
05
#114
1'
1A
b100 }
b110 |
b101 %
1?
1I
1,!
1&!
#120
0*
0'
0D
0A
#126
1'
1A
b101 }
b111 |
b110 %
0?
1>
1K
0,!
1+!
0%!
#130
1*
1D
#132
0'
0A
#138
1'
1A
b110 }
b101 |
b111 %
1?
0J
1,!
0&!
#140
0*
0D
#144
0'
0A
#150
1*
1'
1D
1A
b111 }
b100 |
b1000 %
0?
0>
0=
1<
0K
0,!
0+!
0*!
1)!
1#!
#156
0'
0A
#160
0*
0D
#162
1'
1A
b1000 }
b1100 |
b1001 %
1?
1H
1,!
1&!
#168
0'
0A
#170
1*
1D
#174
1'
1A
b1001 }
b1101 |
b1010 %
0?
1>
1K
0,!
1+!
1%!
#180
0*
0'
0D
0A
#186
1'
1A
b1010 }
b1111 |
b1011 %
1?
1J
1,!
0&!
#190
1*
1D
#192
0'
0A
#198
1'
1A
b1011 }
b1110 |
b1100 %
0?
0>
1=
0K
0,!
0+!
1*!
0$!
#200
0*
0D
#204
0'
0A
#210
1*
1'
1D
1A
b1100 }
b1010 |
b1101 %
1?
0I
1,!
1&!
#216
0'
0A
#220
0*
0D
#222
1'
1A
b1101 }
b1011 |
b1110 %
0?
1>
1K
0,!
1+!
0%!
#228
0'
0A
#230
1*
1D
#234
1'
1A
b1110 }
b1001 |
b1111 %
1?
0J
1,!
0&!
#240
0*
0'
0D
0A
#246
1'
1A
b1111 }
b1000 |
b10000 %
0?
0>
0=
0<
1;
0K
0,!
0+!
0*!
0)!
1(!
1"!
#250
1*
1D
#252
0'
0A
#258
1'
1A
b10000 }
b11000 |
b10001 %
1?
1G
1,!
1&!
0e
#260
0*
0D
#264
0'
0A
#270
1*
1'
1D
1A
b10001 }
b11001 |
b10010 %
0?
1>
1K
0,!
1+!
1%!
#276
0'
0A
#280
0*
0D
#282
1'
1A
b10010 }
b11011 |
b10011 %
1?
1J
1,!
0&!
#288
0'
0A
#290
1*
1D
#294
1'
1A
b10011 }
b11010 |
b10100 %
0?
0>
1=
0K
0,!
0+!
1*!
1$!
#300
0*
0'
0D
0A
#306
1'
1A
b10100 }
b11110 |
b10101 %
1?
1I
1,!
1&!
#310
1*
1D
#312
0'
0A
#318
1'
1A
b10101 }
b11111 |
b10110 %
0?
1>
1K
0,!
1+!
0%!
#320
0*
0D
#324
0'
0A
#330
1*
1'
1D
1A
b10110 }
b11101 |
b10111 %
1?
0J
1,!
0&!
#336
0'
0A
#340
0*
0D
#342
1'
1A
b10111 }
b11100 |
b11000 %
0?
0>
0=
1<
0K
0,!
0+!
0*!
1)!
0#!
#348
0'
0A
#350
1*
1D
#354
1'
1A
b11000 }
b10100 |
b11001 %
1?
0H
1,!
1&!
#360
0*
0'
0D
0A
#366
1'
1A
b11001 }
b10101 |
b11010 %
0?
1>
1K
0,!
1+!
1%!
#370
1*
1D
#372
0'
0A
#378
1'
1A
b11010 }
b10111 |
b11011 %
1?
1J
1,!
0&!
#380
0*
0D
#384
0'
0A
#390
1*
1'
1D
1A
b11011 }
b10110 |
b11100 %
0?
0>
1=
0K
0,!
0+!
1*!
0$!
#396
0'
0A
#400
0*
0D
#402
1'
1A
b11100 }
b10010 |
b11101 %
1?
0I
1,!
1&!
#408
0'
0A
#410
1*
1D
#414
1'
1A
b11101 }
b10011 |
b11110 %
0?
1>
1K
0,!
1+!
0%!
#420
0*
0'
0D
0A
#426
1'
1A
b11110 }
b10001 |
b11111 %
1?
0J
1,!
0&!
#430
1*
1D
#432
0'
0A
#438
1'
1A
b11111 }
b10000 |
b100000 %
0?
0>
0=
0<
0;
1:
0K
0,!
0+!
0*!
0)!
0(!
1'!
1!!
#440
0*
0D
#444
0'
0A
#450
1*
1'
1D
1A
b100000 }
b110000 |
b100001 %
1?
1F
1,!
1&!
1e
#456
0'
0A
#460
0*
0D
#462
1'
1A
b100001 }
b110001 |
b100010 %
0?
1>
1K
0,!
1+!
1%!
#468
0'
0A
#470
1*
1D
#474
1'
1A
b100010 }
b110011 |
b100011 %
1?
1J
1,!
0&!
#480
0*
0'
0D
0A
#486
1'
1A
b100011 }
b110010 |
b100100 %
0?
0>
1=
0K
0,!
0+!
1*!
1$!
#490
1*
1D
#492
0'
0A
#498
1'
1A
b100100 }
b110110 |
b100101 %
1?
1I
1,!
1&!
#500
0*
0D
#504
0'
0A
#510
1*
1'
1D
1A
b100101 }
b110111 |
b100110 %
0?
1>
1K
0,!
1+!
0%!
#516
0'
0A
#520
0*
0D
#522
1'
1A
b100110 }
b110101 |
b100111 %
1?
0J
1,!
0&!
#528
0'
0A
#530
1*
1D
#534
1'
1A
b100111 }
b110100 |
b101000 %
0?
0>
0=
1<
0K
0,!
0+!
0*!
1)!
1#!
#540
0*
0'
0D
0A
#546
1'
1A
b101000 }
b111100 |
b101001 %
1?
1H
1,!
1&!
#550
1*
1D
#552
0'
0A
#558
1'
1A
b101001 }
b111101 |
b101010 %
0?
1>
1K
0,!
1+!
1%!
#560
0*
0D
#564
0'
0A
#570
1*
1'
1D
1A
b101010 }
b111111 |
b101011 %
1?
1J
1,!
0&!
#576
0'
0A
#580
0*
0D
#582
1'
1A
b101011 }
b111110 |
b101100 %
0?
0>
1=
0K
0,!
0+!
1*!
0$!
#588
0'
0A
#590
1*
1D
#594
1'
1A
b101100 }
b111010 |
b101101 %
1?
0I
1,!
1&!
#600
0*
0'
0D
0A
#606
1'
1A
b101101 }
b111011 |
b101110 %
0?
1>
1K
0,!
1+!
0%!
#610
1*
1D
#612
0'
0A
#618
1'
1A
b101110 }
b111001 |
b101111 %
1?
0J
1,!
0&!
#620
0*
0D
#624
0'
0A
#630
1*
1'
1D
1A
b101111 }
b111000 |
b110000 %
0?
0>
0=
0<
1;
0K
0,!
0+!
0*!
0)!
1(!
0"!
#636
0'
0A
#640
0*
0D
#642
1'
1A
b110000 }
b101000 |
b110001 %
1?
0G
1,!
1&!
0d
1b
#648
0'
0A
#650
1*
1D
#654
1'
1A
b110001 }
b101001 |
b110010 %
0?
1>
1K
0,!
1+!
1%!
#660
0*
0'
0D
0A
#666
1'
1A
b110010 }
b101011 |
b110011 %
1?
1J
1,!
0&!
#670
1*
1D
#672
0'
0A
#678
1'
1A
b110011 }
b101010 |
b110100 %
0?
0>
1=
0K
0,!
0+!
1*!
1$!
#680
0*
0D
#684
0'
0A
#690
1*
1'
1D
1A
b110100 }
b101110 |
b110101 %
1?
1I
1,!
1&!
#696
0'
0A
#700
0*
0D
#702
1'
1A
b110101 }
b101111 |
b110110 %
0?
1>
1K
0,!
1+!
0%!
#708
0'
0A
#710
1*
1D
#714
1'
1A
b110110 }
b101101 |
b110111 %
1?
0J
1,!
0&!
#720
0*
0'
0D
0A
#726
1'
1A
b110111 }
b101100 |
b111000 %
0?
0>
0=
1<
0K
0,!
0+!
0*!
1)!
0#!
#730
1*
1D
#732
0'
0A
#738
1'
1A
b111000 }
b100100 |
b111001 %
1?
0H
1,!
1&!
#740
0*
0D
#744
0'
0A
#750
1*
1'
1D
1A
b111001 }
b100101 |
b111010 %
0?
1>
1K
0,!
1+!
1%!
#756
0'
0A
#760
0*
0D
#762
1'
1A
b111010 }
b100111 |
b111011 %
1?
1J
1,!
0&!
#768
0'
0A
#770
1*
1D
#774
1'
1A
b111011 }
b100110 |
b111100 %
0?
0>
1=
0K
0,!
0+!
1*!
0$!
#780
0*
0'
0D
0A
#786
1'
1A
b111100 }
b100010 |
b111101 %
1?
0I
1,!
1&!
#790
1*
1D
#792
0'
0A
#798
1'
1A
b111101 }
b100011 |
b111110 %
0?
1>
1K
0,!
1+!
0%!
#800
0*
0D
#804
0'
0A
#810
1*
1'
1D
1A
b111110 }
b100001 |
b111111 %
1?
0J
1,!
0&!
#816
0'
0A
#820
0*
0D
#822
1'
1A
b111111 }
b100000 |
b1000000 %
0?
0>
0=
0<
0;
0:
19
0K
0,!
0+!
0*!
0)!
0(!
0'!
0!!
#828
0'
0A
#830
1*
1D
#834
1'
1A
b0 }
b0 |
b1000001 %
1?
0F
1,!
1&!
1d
0_
1~
1{
0,!
14
0&!
#840
0*
0'
0D
0A
#846
1'
1A
0&
1-
0@
